json_model_widget/__init__.py
json_model_widget/widgets.py
json_model_widget/__pycache__/__init__.cpython-39.pyc
json_model_widget/__pycache__/widgets.cpython-39.pyc
json_model_widget/static/json_model_widget/css/styles.css
json_model_widget/static/json_model_widget/images/icon-deletepair.svg
json_model_widget/templates/json_model_widget/json_model_widget.html
django_json_model_widget-0.0.7.dist-info/METADATA
django_json_model_widget-0.0.7.dist-info/WHEEL
django_json_model_widget-0.0.7.dist-info/top_level.txt
django_json_model_widget-0.0.7.dist-info/RECORD
