Metadata-Version: 2.1
Name: django-json-model-widget
Version: 0.0.7
Summary: Custom flat json field widget for model pairs
Home-page: https://github.com/galij899/django-json-model-widget
Author: Oleg Galichkin
Author-email: galij899@yandex.ru
License: MIT
Download-URL: https://pypi.org/project/django-json-model-widget/
Keywords: django,django-admin,django-admin-widget
Platform: UNKNOWN
